fermpy/__init__.py
fermpy/bases.py
fermpy/example.py
fermpy/hamiltonian_constructors.py
fermpy/operator_representation.py
fermpy/operator_sum.py
fermpy/operators.py
fermpy-0.0.2.dist-info/METADATA
fermpy-0.0.2.dist-info/WHEEL
fermpy-0.0.2.dist-info/licenses/LICENSE
fermpy-0.0.2.dist-info/RECORD
