Metadata-Version: 2.1
Name: fermpy
Version: 0.0.2
Summary: Package for exactly solving low-dimensional fermionic Hamiltonians
Project-URL: Homepage, https://github.com/emilfrost/fermpy
Author-email: Emil Frost <emiljpfrost@gmail.com>
License-File: LICENSE
Keywords: Hamiltonian,condensed matter,exact diagonalization,fermion,physics,sparse
Classifier: License :: OSI Approved :: MIT License
Classifier: Operating System :: OS Independent
Classifier: Programming Language :: Python :: 3
Requires-Python: >=3.10
Requires-Dist: numpy>=1.20
Requires-Dist: scipy>=1.10.0
